lesp/__init__.py
lesp/autocorrect.py
lesp-1.1.1.dist-info/WHEEL
lesp-1.1.1.dist-info/METADATA
lesp-1.1.1.dist-info/RECORD
