Metadata-Version: 2.1
Name: lesp
Version: 1.1.1
Summary: LESP is a lightweight, efficient spelling proofreader written in Python. It's designed to be easy to use and lightweight, while still providing a decent result when checking for spelling errors. Resource consumption is kept to a minimum, and the program is designed to be as fast as possible.
Author-email: Lyubomir Ternavskiy <ternavski103@gmail.com>
Requires-Python: >=3.6
Classifier: Development Status :: 5 - Production/Stable
Classifier: Programming Language :: Python
Project-URL: Homepage, https://github.com/LyubomirT/lesp
Project-URL: Issues, https://github.com/LyubomirT/lesp/issues
